fast_matrix_market/__init__.py
fast_matrix_market/_fmm_core.cp38-win_amd64.pyd
fast_matrix_market/_fmm_core.cpp
fast_matrix_market/_fmm_core.hpp
fast_matrix_market/_fmm_core_read_array.cpp
fast_matrix_market/_fmm_core_read_coo.cpp
fast_matrix_market/_fmm_core_write_array.cpp
fast_matrix_market/_fmm_core_write_coo_32.cpp
fast_matrix_market/_fmm_core_write_coo_64.cpp
fast_matrix_market/_fmm_core_write_csc_32.cpp
fast_matrix_market/_fmm_core_write_csc_64.cpp
fast_matrix_market/pystreambuf.h
include/dragonbox-1.1.3/dragonbox/dragonbox.h
include/dragonbox-1.1.3/dragonbox/dragonbox_to_chars.h
include/ryu/ryu.h
lib/cmake/dragonbox-1.1.3/dragonboxConfig.cmake
lib/cmake/dragonbox-1.1.3/dragonboxConfigVersion.cmake
lib/cmake/dragonbox-1.1.3/dragonboxTargets-release.cmake
lib/cmake/dragonbox-1.1.3/dragonboxTargets.cmake
lib/dragonbox_to_chars.lib
lib/ryu.lib
fast_matrix_market-1.7.6.dist-info/METADATA
fast_matrix_market-1.7.6.dist-info/WHEEL
fast_matrix_market-1.7.6.dist-info/entry_points.txt
fast_matrix_market-1.7.6.dist-info/licenses/LICENSE.txt
fast_matrix_market-1.7.6.dist-info/RECORD
