Metadata-Version: 2.1
Name: fast-matrix-market
Version: 1.7.6
Summary: Fast and full-featured Matrix Market file I/O
Home-page: https://github.com/alugowski/fast_matrix_market
Author: Adam Lugowski
Classifier: Development Status :: 5 - Production/Stable 
Classifier: Intended Audience :: Science/Research
Classifier: Intended Audience :: Developers
Classifier: License :: OSI Approved :: BSD License
Classifier: Programming Language :: Python :: 3 :: Only
Classifier: Programming Language :: Python :: 3.7
Classifier: Programming Language :: Python :: 3.8
Classifier: Programming Language :: Python :: 3.9
Classifier: Programming Language :: Python :: 3.10
Classifier: Programming Language :: Python :: 3.11
Classifier: Programming Language :: Python :: 3.12
Classifier: Topic :: Software Development :: Libraries
Classifier: Topic :: Scientific/Engineering
Project-URL: Homepage, https://github.com/alugowski/fast_matrix_market
Project-URL: Repository, https://github.com/alugowski/fast_matrix_market
Requires-Python: >=3.7
Provides-Extra: test
Provides-Extra: testmin
Requires-Dist: pytest; extra == "test"
Requires-Dist: scipy; extra == "test"
Requires-Dist: threadpoolctl; extra == "test"
Requires-Dist: pytest; extra == "testmin"
Requires-Dist: threadpoolctl; extra == "testmin"
License-File: LICENSE.txt
